admesh_weave/__init__.py
admesh_weave/client.py
admesh_weave/py.typed
admesh_weave/types.py
admesh_weave_python-0.3.0.dist-info/METADATA
admesh_weave_python-0.3.0.dist-info/WHEEL
admesh_weave_python-0.3.0.dist-info/licenses/LICENSE
admesh_weave_python-0.3.0.dist-info/RECORD
