Metadata-Version: 2.3
Name: admesh-weave-python
Version: 0.3.0
Summary: Python SDK for integrating AdMesh Weave Ad Format into AI-powered applications
Project-URL: Homepage, https://github.com/GouniManikumar12/admesh-weave-python
Project-URL: Repository, https://github.com/GouniManikumar12/admesh-weave-python
Author-email: AdMesh <mani@useadmesh.com>
License: MIT
Classifier: Intended Audience :: Developers
Classifier: License :: OSI Approved :: MIT License
Classifier: Operating System :: MacOS
Classifier: Operating System :: Microsoft :: Windows
Classifier: Operating System :: OS Independent
Classifier: Operating System :: POSIX
Classifier: Operating System :: POSIX :: Linux
Classifier: Programming Language :: Python :: 3.8
Classifier: Programming Language :: Python :: 3.9
Classifier: Programming Language :: Python :: 3.10
Classifier: Programming Language :: Python :: 3.11
Classifier: Programming Language :: Python :: 3.12
Classifier: Topic :: Software Development :: Libraries :: Python Modules
Classifier: Typing :: Typed
Requires-Python: >=3.8
Requires-Dist: httpx<1,>=0.23.0
Requires-Dist: typing-extensions<5,>=4.5.0
